flexmatcher/__init__.py
flexmatcher/flexmatcher.py
flexmatcher/classify/__init__.py
flexmatcher/classify/charDistClassifier.py
flexmatcher/classify/classifier.py
flexmatcher/classify/knnClassifier.py
flexmatcher/classify/nGramClassifier.py
flexmatcher/utils/__init__.py
flexmatcher/utils/customAnalyzer.py
flexmatcher-1.0.4.dist-info/DESCRIPTION.rst
flexmatcher-1.0.4.dist-info/METADATA
flexmatcher-1.0.4.dist-info/RECORD
flexmatcher-1.0.4.dist-info/WHEEL
flexmatcher-1.0.4.dist-info/metadata.json
flexmatcher-1.0.4.dist-info/top_level.txt
