Metadata-Version: 2.0
Name: flexmatcher
Version: 1.0.4
Summary: FlexMatcher is a schema matching package in Python which handles the problem of matching multiple schemas to a single mediated schema.
Home-page: https://github.com/biggorilla-gh/flexmatcher
Author: BigGorilla Team
Author-email: thebiggorilla.team@gmail.com
License: Apache Software License 2.0
Keywords: flexmatcher
Platform: UNKNOWN
Classifier: Development Status :: 2 - Pre-Alpha
Classifier: Intended Audience :: Developers
Classifier: License :: OSI Approved :: Apache Software License
Classifier: Natural Language :: English
Classifier: Programming Language :: Python :: 2
Classifier: Programming Language :: Python :: 2.7
Classifier: Programming Language :: Python :: 3
Classifier: Programming Language :: Python :: 3.5
Classifier: Programming Language :: Python :: 3.6
Requires-Dist: Munkres
Requires-Dist: numpy
Requires-Dist: pandas
Requires-Dist: python-Levenshtein (==0.12.0)
Requires-Dist: scikit-learn (>=0.18)
Requires-Dist: scipy
